stressrunner/__init__.py
stressrunner/mail.py
stressrunner/report.py
stressrunner/runner.py
stressrunner/test/__init__.py
stressrunner/test/test.py
stressrunner-1.1.13.dist-info/LICENSE
stressrunner-1.1.13.dist-info/METADATA
stressrunner-1.1.13.dist-info/WHEEL
stressrunner-1.1.13.dist-info/top_level.txt
stressrunner-1.1.13.dist-info/RECORD
