Metadata-Version: 2.1
Name: stressrunner
Version: 1.1.13
Summary: A stressrunner similar as TextTestRunner for stress test, support for html report.
Home-page: https://github.com/txu2k8/stress-runner
Author: tao.xu
Author-email: tao.xu2008@outlook.com
License: MIT
Keywords: stress,stressrunner,html,unittest
Platform: UNKNOWN
Classifier: Intended Audience :: Developers
Classifier: License :: OSI Approved :: MIT License
Classifier: Natural Language :: English
Classifier: Programming Language :: Python :: 3
Requires-Python: >=3.4.0
Requires-Dist: coloredlogs
